LICENSE
MANIFEST.in
README.md
setup.py
django_log_register.egg-info/PKG-INFO
django_log_register.egg-info/SOURCES.txt
django_log_register.egg-info/dependency_links.txt
django_log_register.egg-info/top_level.txt
log_register/__init__.py
log_register/actions.py
log_register/admin.py
log_register/managers.py
log_register/models.py
log_register/settings.py
log_register/tests.py
log_register/views.py